tamar_message_gateway/__init__.py
tamar_message_gateway/client.py
tamar_message_gateway/config/__init__.py
tamar_message_gateway/config/config.py
tamar_message_gateway/core/__init__.py
tamar_message_gateway/core/mysql_service.py
tamar_message_gateway/core/rabbitmq_service.py
tamar_message_gateway/core/redis_service.py
tamar_message_gateway/exceptions/__init__.py
tamar_message_gateway/exceptions/errors.py
tamar_message_gateway/models/__init__.py
tamar_message_gateway/models/base.py
tamar_message_gateway/models/push_messages.py
tamar_message_gateway/utils/__init__.py
tamar_message_gateway/utils/backoff.py
tamar_message_gateway-0.1.4.dist-info/licenses/LICENSE
tamar_message_gateway-0.1.4.dist-info/METADATA
tamar_message_gateway-0.1.4.dist-info/WHEEL
tamar_message_gateway-0.1.4.dist-info/top_level.txt
tamar_message_gateway-0.1.4.dist-info/RECORD
