Metadata-Version: 2.4
Name: tamar-message-gateway
Version: 0.1.4
Summary: 用于与 Tamar 消息网关交互的 Python SDK
Author-email: leon <leon.liang@tamaredge.ai>
License-Expression: MIT
Keywords: message gateway,tamar,websocket
Classifier: Programming Language :: Python :: 3
Classifier: Programming Language :: Python :: 3.8
Classifier: Programming Language :: Python :: 3.9
Classifier: Programming Language :: Python :: 3.10
Classifier: Programming Language :: Python :: 3.11
Classifier: Programming Language :: Python :: 3.12
Classifier: Operating System :: OS Independent
Classifier: Topic :: Software Development :: Libraries :: Python Modules
Classifier: Intended Audience :: Developers
Requires-Python: >=3.8
License-File: LICENSE
Requires-Dist: pika>=1.3.2
Requires-Dist: SQLAlchemy>=2.0.0
Requires-Dist: redis>=5.0.0
Requires-Dist: PyMySQL==1.1.1
Dynamic: license-file
